run_snapshot_tests/__init__.py
run_snapshot_tests/_run_snapshot_tests.py
run_snapshot_tests/example.py
run_snapshot_tests/fixed_format_code.py
run_snapshot_tests/fixed_snapshot.py
run_snapshot_tests-0.3.1.dist-info/METADATA
run_snapshot_tests-0.3.1.dist-info/WHEEL
run_snapshot_tests-0.3.1.dist-info/licenses/LICENSE
run_snapshot_tests-0.3.1.dist-info/RECORD
