Metadata-Version: 2.4
Name: run-snapshot-tests
Version: 0.3.1
Summary: Runner for Python [inline-snapshot](https://github.com/15r10nk/inline-snapshot/) tests with a better interface and cleaner terminal output.
Author-email: Mark Lidenberg <marklidenberg@gmail.com>
License: MIT
License-File: LICENSE
Classifier: Intended Audience :: Developers
Classifier: License :: OSI Approved :: MIT License
Classifier: Programming Language :: Python :: 3
Classifier: Programming Language :: Python :: 3.8
Classifier: Programming Language :: Python :: 3.9
Classifier: Programming Language :: Python :: 3.10
Classifier: Programming Language :: Python :: 3.11
Classifier: Programming Language :: Python :: 3.12
Classifier: Programming Language :: Python :: 3.13
Requires-Python: >=3.8
Requires-Dist: inline-snapshot==0.8.0
Requires-Dist: pytest>=8.3.5
Provides-Extra: dev
Requires-Dist: build>=1.2.2.post1; extra == 'dev'
Requires-Dist: dony>=0.2.1; extra == 'dev'
Requires-Dist: twine>=6.1.0; extra == 'dev'
